{
    "Sheet1": [
        {
            "title": "The Complete 2022 Web Development Bootcamp",
            "createdBy": "Avinas Jain",
            "description": "Take one of Udemy’s range of Python courses and learn how to code using this incredibly useful language.",
            "price": "13.99",
            "dos": "24-Apr-22",
            "enrolled": "75",
            "rating": "4.7"
        },
        {
            "title": "The Complete JavaScript Course 2022: From Zero to Expert!",
            "createdBy": "Jonas Manhatton",
            "description": "Take one of Udemy’s range of Python courses and learn how to code using this incredibly useful language.",
            "price": "84.99",
            "dos": "22-Apr-22",
            "enrolled": "125",
            "rating": "4.8"
        },
        {
            "title": "iOS & Swift - The Complete iOS App Development Bootcamp",
            "createdBy": "Dr. Angela Yu",
            "description": "Take one of Udemy’s range of Python courses and learn how to code using this incredibly useful language.",
            "price": "12.99",
            "dos": "31-May-22",
            "enrolled": "54",
            "rating": "4.5"
        },
        {
            "title": "Ultimate AWS Certified Solutions Architect Associate 2022",
            "createdBy": "Stephane Maarek",
            "description": "Full Practice Exam | Learn Cloud Computing | Pass the AWS Certified Solutions Architect Associate Certification SAA-C02!",
            "price": "13.99",
            "dos": "5-Jan-22",
            "enrolled": "46",
            "rating": "4.9"
        }
    ]
}